[
    {
        "title": "Project 1: Expository Visualization",
        "year": "2025",
        "image": "https://vis-society.github.io/labs/2/images/empty.svg",
        "description": "In this assignment, you will design an expository visualization to clearly communicate an idea based on a small data set. In addition, you must provide a rigorous rationale for your design choices. You should in theory be ready to explain the contribution of every pixel in the display towards your expository goals. "
    },
    {
        "title": "Project 2: Deceptive Visualization",
        "year": "2025",
        "image": "https://vis-society.github.io/labs/2/images/empty.svg",
        "description": "Data visualizations are becoming a key medium for the public to understand news and information. It’s crucial to recognize how the design of a visualization can affect what people understand and remember from the data. In this task, you need to pick a dataset you find interesting and create two static visualizations using the same dataset. The first should be a truthful representation of the data. The second should be a deceptive visualization, designed to deceive the viewer. However, you should avoid clear distortions or leaving out information for this deceptive visualization."
    },
    {
        "title": "Project 3: Interactive Visualization",
        "year": "2025",
        "image": "https://vis-society.github.io/labs/2/images/empty.svg",
        "description": "Not release yet"
    },
    {
        "title": "Final Project of DSC106",
        "year": "2025",
        "image": "https://vis-society.github.io/labs/2/images/empty.svg",
        "description": "Not release yet"
    },
    {
        "title": "Card Game Design",
        "year": "2022",
        "image": "https://vis-society.github.io/labs/2/images/empty.svg",
        "description": "Design a shuffler for a deck of cards."
    },
    {
        "title": "Board Game Design",
        "year": "2023",
        "image": "https://vis-society.github.io/labs/2/images/empty.svg",
        "description": "Design a board game that could promote environmental protection."
    },
    {
        "title": "DSC80 Project1: Gradebook",
        "year": "2024",
        "image": "https://vis-society.github.io/labs/2/images/empty.svg",
        "description": "Analyze on the gradeboook of dsc80 students"
    },
    {
        "title": "DSC80 Project2: Covid Vaccination",
        "year": "2024",
        "image": "https://vis-society.github.io/labs/2/images/empty.svg",
        "description": "Analyze on the vaccination of COVID in 2020"
    },
    {
        "title": "DSC80 Project3: Topic",
        "year": "2024",
        "image": "https://vis-society.github.io/labs/2/images/empty.svg",
        "description": "Analyze on the topics of Netflix series"
    },
    {
        "title": "DSC80 Project4: Language Models",
        "year": "2024",
        "image": "https://vis-society.github.io/labs/2/images/empty.svg",
        "description": "Analyze on the language models used the most"
    },
    {
        "title": "DSC80 Project5: Prediction",
        "year": "2024",
        "image": "https://vis-society.github.io/labs/2/images/empty.svg",
        "description": "Practice prediction based on given dataset"
    },
    {
        "title": "MATH189 Project",
        "year": "2025",
        "image": "https://vis-society.github.io/labs/2/images/empty.svg",
        "description": "Not release yet"
    },
    {
        "title": "DSC106 lab07: Bikewatching",
        "description": "Visualization of Bike Traffic and Station Situation in Boston ",
        "year": "2025",
        "url": "https://cheriexiao.github.io/bikewatching/", 
        "image": "https://github.com/CherieXiao/portfolio/blob/main/images/bikewatching.png"
    }
]